Metadata-Version: 1.0
Name: chineseMarkov
Version: 0.1.3
Summary: Chinese Sentence Generator
Home-page: https://github.com/Kimice/ChineseMarkov
Author: Kimice
Author-email: kimiceqc@gmail.com
License: GPLv3
Platform: UNKNOWN
